setup.py
src/seleniumqt/AddUserCase.py
src/seleniumqt/Image.py
src/seleniumqt/__init__.py
src/seleniumqt/adb.py
src/seleniumqt/attr_ele.py
src/seleniumqt/base.py
src/seleniumqt/case.py
src/seleniumqt/compress_image.py
src/seleniumqt/dbsql.py
src/seleniumqt/ele_high_show.py
src/seleniumqt/is_alpha.py
src/seleniumqt/net.py
src/seleniumqt/objectTree.py
src/seleniumqt/oss.py
src/seleniumqt/page.py
src/seleniumqt/project.py
src/seleniumqt/report.py
src/seleniumqt/responese.py
src/seleniumqt/screen_change.py
src/seleniumqt/sys.py
src/seleniumqt/user.py
src/seleniumqt.egg-info/PKG-INFO
src/seleniumqt.egg-info/SOURCES.txt
src/seleniumqt.egg-info/dependency_links.txt
src/seleniumqt.egg-info/top_level.txt